orbit_etl/__init__.py
orbit_etl/clean.py
orbit_etl/extract.py
orbit_etl/load.py
orbit_etl-0.9.dist-info/METADATA
orbit_etl-0.9.dist-info/WHEEL
orbit_etl-0.9.dist-info/top_level.txt
orbit_etl-0.9.dist-info/RECORD
