Metadata-Version: 2.1
Name: orbit-etl
Version: 0.9
Summary: Package for extracting data from MySQL and loading to GCS in CSV
Home-page: https://github.com/orbitremit/orbit_etl
Author: Benjamin Jeffrey
Author-email: ben.jeffrey@orbitremit.com
Classifier: Programming Language :: Python :: 3
Classifier: License :: OSI Approved :: MIT License
Classifier: Operating System :: OS Independent
Requires-Python: >=3.8
Requires-Dist: pymysql
Requires-Dist: google-cloud-secret-manager
Requires-Dist: google-cloud-storage
Requires-Dist: configparser
Requires-Dist: dask
Requires-Dist: dask[dataframe]
